{"cameraMode":{"drawMode":0,"name":"Shaded","section":"Shading Mode"},"sceneLighting":true,"audioPlay":false,"sceneViewState":{"m_AlwaysRefresh":false,"showFog":true,"showSkybox":true,"showFlares":true,"showImageEffects":true,"showParticleSystems":true,"showVisualEffectGraphs":true,"m_FxEnabled":true},"in2DMode":false,"pivot":{"x":1.9853731393814088,"y":-9.797304153442383,"z":35.097190856933597},"rotation":{"x":-0.14189110696315766,"y":-0.042758747935295108,"z":0.0060883802361786369,"w":-0.9889678955078125},"size":33.882389068603519,"orthographic":false}